<?xml version="1.0" encoding="UTF-8"?><record_update table="sc_cat_item_catalog">
    <sc_cat_item_catalog action="INSERT_OR_UPDATE">
        <sc_cat_item display_value="Report a Safety Issue">c8ffe6f3db5123006300f53a2996192b</sc_cat_item>
        <sc_catalog display_value="Service Catalog">e0d08b13c3330100c8b837659bba8fb4</sc_catalog>
        <sys_class_name>sc_cat_item_catalog</sys_class_name>
        <sys_created_by>admin</sys_created_by>
        <sys_created_on>2018-10-29 02:20:33</sys_created_on>
        <sys_id>84ff6a37db5123006300f53a299619e8</sys_id>
        <sys_mod_count>0</sys_mod_count>
        <sys_name>Service Catalog.Report a Safety Issue</sys_name>
        <sys_package display_value="Safety" source="x_284403_safety">8697da33db1123006300f53a299619b4</sys_package>
        <sys_policy/>
        <sys_scope display_value="Safety">8697da33db1123006300f53a299619b4</sys_scope>
        <sys_update_name>sc_cat_item_catalog_84ff6a37db5123006300f53a299619e8</sys_update_name>
        <sys_updated_by>admin</sys_updated_by>
        <sys_updated_on>2018-10-29 02:20:33</sys_updated_on>
    </sc_cat_item_catalog>
</record_update>
